pytest_kafka_broker/__init__.py
pytest_kafka_broker/py.typed
pytest_kafka_broker-0.4.0.dist-info/METADATA
pytest_kafka_broker-0.4.0.dist-info/WHEEL
pytest_kafka_broker-0.4.0.dist-info/entry_points.txt
pytest_kafka_broker-0.4.0.dist-info/top_level.txt
pytest_kafka_broker-0.4.0.dist-info/RECORD
