Metadata-Version: 2.4
Name: pytest-kafka-broker
Version: 0.4.0
Summary: Pytest plugin to run a single-broker Kafka cluster
Author-email: Leo Singer <leo.singer@ligo.org>
License-Expression: Apache-2.0
Project-URL: source, https://git.ligo.org/ultra-swift/pytest-kafka-broker
Project-URL: documentation, https://pytest-kafka-broker.readthedocs.io/
Classifier: Framework :: Pytest
Classifier: Topic :: System :: Networking
Requires-Python: >=3.11
Requires-Dist: astropy
Requires-Dist: confluent-kafka
Requires-Dist: rich
Requires-Dist: pytest-asyncio
Provides-Extra: docs
Requires-Dist: sphinx-astropy[confv2]; extra == "docs"
Requires-Dist: sphinx-automodapi>=0.20.0; extra == "docs"
